{
    "silent_assassin_title" : "无声刺客",
    "silent_assassin_desc" : "自定义无声刺客玩法",
    "sa_num_pagers" : "全体可回答对讲机数量",
    "sa_num_pagers_desc" : "所有玩家可回答对讲机的数量",
    "sa_num_pagers_per_player" : "玩家可回答对讲机数量",
    "sa_num_pagers_per_player_desc" : "单个玩家可以回答的对讲机数量",
    "sa_pagers_0" : "0",
    "sa_pagers_1" : "1",
    "sa_pagers_2" : "2",
    "sa_pagers_3" : "3",
    "sa_pagers_4" : "4",
    "sa_enabled_title" : "启用无声刺客",
    "sa_enabled_desc" : "启用无声刺客mod",
    "sa_kill_pager_enabled_title" : "隐匿击杀无对讲机",
    "sa_kill_pager_enabled_desc" : "如果设置的话，当无人看守的保安被隐匿击杀时，对讲机将不会发出声音"
    "sa_pager_bonus_enabled_title" : "启用对讲机隐匿奖金",
    "sa_pager_bonus_enabled_desc" : "根据允许和使用的寻呼机，为任务启用修改后的隐匿增值。 这是试验功能并仅主机",
    "sa_matchmaking_title" : "配对",
    "sa_matchmaking_desc" : "在搜寻Crime.net时，是否要求或避免无声刺客大厅",
    "sa_matchmaking_both" : "两者",
    "sa_matchmaking_require" : "要求",
    "sa_matchmaking_avoid" : "避免",
	"sa_pager_detection_threshold_title" : "寻呼机检测阈值",
    "sa_pager_detection_threshold_desc" : "如果检测进度表超过了这个百分比，则传呼机无论如何都会关闭",
    "sa_lobby_notice_1" : "主持人正在运行“无声的刺客”。 ",
    "sa_lobby_notice_2" : "杀死无人看守的卫士不会触发传呼机。 ",
    "sa_lobby_notice_3" : "最多允许$num_pagers;的寻呼机，每个玩家可以回答最多$num_per_player;寻呼机。如果检测过程达到$pager_detection_threshold_pct;%，则寻呼机关闭。"
}